[
  {
    "id": "reika_original_song19",
    "title": "硝子のシャボン玉",
    "artist": "れいか",
    "key": "原曲キー",
    "rating": 0,
    "titleKana": "がらすのしゃぼんだま",
    "artistKana": "れいか",
    "year": "2025",
    "genre": "",
    "memo": "歌姫れいか／日本クラウン 「とわず語りの数え唄」カップリング曲」"
  },
  {
    "id": "reika_original_song18",
    "title": "とわず語りの数え唄",
    "artist": "れいか",
    "key": "原曲キー",
    "rating": 0,
    "titleKana": "とわずがたりのかぞえうた",
    "artistKana": "れいか",
    "year": "2025",
    "genre": "",
    "memo": "歌姫れいか／日本クラウン"
  },
  {
    "id": "reika_original_song17",
    "title": "東京ボレロ",
    "artist": "れいか",
    "key": "原曲キー",
    "rating": 0,
    "titleKana": "とうきょうぼれろ",
    "artistKana": "れいか",
    "year": "2023",
    "genre": "",
    "memo": "歌姫れいか／日本クラウン 「OSAKAレイニーブルース」カップリング曲"
  },
  {
    "id": "reika_original_song16",
    "title": "OSAKAレイニーブルース",
    "artist": "れいか",
    "key": "原曲キー",
    "rating": 0,
    "titleKana": "おおさかれいにーぶるーす",
    "artistKana": "れいか",
    "year": "2023",
    "genre": "",
    "memo": "歌姫れいか／日本クラウン"
  },
  {
    "id": "reika_original_song15",
    "title": "紅い月のアモーレ",
    "artist": "れいか",
    "key": "原曲キー",
    "rating": 0,
    "titleKana": "あかいつきのあもーれ",
    "artistKana": "れいか",
    "year": "2020",
    "genre": "",
    "memo": "歌姫れいか／日本クラウン 「貯金好きな女」カップリング曲"
  },
  {
    "id": "reika_original_song14",
    "title": "貯金好きな女",
    "artist": "れいか",
    "key": "原曲キー",
    "rating": 0,
    "titleKana": "ちょきんすきなおんな",
    "artistKana": "れいか",
    "year": "2020",
    "genre": "",
    "memo": "歌姫れいか／日本クラウン"
  },
  {
    "id": "reika_original_song13",
    "title": "醜聞は夜作られる",
    "artist": "れいか",
    "key": "原曲キー",
    "rating": 0,
    "titleKana": "すきゃんだる、しゅうぶんはよるつくられる",
    "artistKana": "れいか",
    "year": "2018",
    "genre": "",
    "memo": "歌姫れいか／日本クラウン 「優しい嘘をください」カップリング曲"
  },
  {
    "id": "reika_original_song12",
    "title": "優しい嘘をください",
    "artist": "れいか",
    "key": "原曲キー",
    "rating": 0,
    "titleKana": "やさしいうそをください",
    "artistKana": "れいか",
    "year": "2018",
    "genre": "",
    "memo": "歌姫れいか／日本クラウン 作詞作曲:杉本眞人 = 杉本眞人氏によるれいかソング時代の幕開け、れいか新世界が始まる"
  },
  {
    "id": "reika_original_song11",
    "title": "憧れのひと",
    "artist": "れいか",
    "key": "原曲キー",
    "rating": 0,
    "titleKana": "あこがれのひと",
    "artistKana": "れいか",
    "year": "2015",
    "genre": "",
    "memo": "れいか 「女のサンバ」カップリング曲"
  },
  {
    "id": "reika_original_song10",
    "title": "女のサンバ",
    "artist": "れいか",
    "key": "原曲キー",
    "rating": 0,
    "titleKana": "おんなのさんば",
    "artistKana": "れいか",
    "year": "2015",
    "genre": "",
    "memo": "れいか 有線演歌歌謡曲3位"
  },
  {
    "id": "reika_original_song9",
    "title": "アモーレ・ミオ〜愛する人〜",
    "artist": "れいか",
    "key": "原曲キー",
    "rating": 0,
    "titleKana": "あもーれみお",
    "artistKana": "れいか",
    "year": "2013",
    "genre": "",
    "memo": "れいか 「奪いたいLOVE」のカップリング曲"
  },
  {
    "id": "reika_original_song8",
    "title": "奪いたいLOVE",
    "artist": "れいか",
    "key": "原曲キー",
    "rating": 0,
    "titleKana": "うばいたいあい",
    "artistKana": "れいか",
    "year": "2013",
    "genre": "",
    "memo": "れいか"
  },
  {
    "id": "reika_original_song7",
    "title": "Tango of tears〜そしてサヨナラ",
    "artist": "れいか",
    "key": "原曲キー",
    "rating": 0,
    "titleKana": "たんごおぶてぃあーず",
    "artistKana": "れいか",
    "year": "2012",
    "genre": "",
    "memo": "れいか 「嘘つき・・・あんた」のカップリング曲"
  },
  {
    "id": "reika_original_song6",
    "title": "嘘つき・・・あんた",
    "artist": "れいか",
    "key": "原曲キー",
    "rating": 0,
    "titleKana": "うそつきあんた",
    "artistKana": "れいか",
    "year": "2012",
    "genre": "",
    "memo": "れいか"
  },
  {
    "id": "reika_original_song5",
    "title": "ぶきっちょのノラ",
    "artist": "れいか",
    "key": "原曲キー",
    "rating": 0,
    "titleKana": "ぶきっちょののら",
    "artistKana": "れいか",
    "year": "2009",
    "genre": "",
    "memo": "れいか 「歌舞伎町のノラ」の子ども向けバージョン"
  },
  {
    "id": "reika_original_song4",
    "title": "雲雀",
    "artist": "れいか",
    "key": "原曲キー",
    "rating": 0,
    "titleKana": "ひばり",
    "artistKana": "れいか",
    "year": "2009",
    "genre": "演歌",
    "memo": "れいか 「歌舞伎町のノラ」のカップリング曲"
  },
  {
    "id": "reika_original_song3",
    "title": "歌舞伎町のノラ",
    "artist": "れいか",
    "key": "原曲キー",
    "rating": 0,
    "titleKana": "かぶきちょうののら",
    "artistKana": "れいか",
    "year": "2009",
    "genre": "",
    "memo": "れいか　メジャー　デビュー曲"
  },
  {
    "id": "reika_original_song2",
    "title": "I miss you",
    "artist": "れいか",
    "key": "原曲キー",
    "rating": 0,
    "titleKana": "あいみすゆー",
    "artistKana": "れいか",
    "year": "2006",
    "genre": "バラード",
    "memo": "れいか「水野れいか」時代楽曲"
  },
  {
    "id": "reika_original_song1",
    "title": "AI",
    "artist": "れいか",
    "key": "原曲キー",
    "rating": 0,
    "titleKana": "あい",
    "artistKana": "れいか",
    "year": "2006",
    "genre": "Pops",
    "memo": "れいか「水野れいか」時代楽曲"
  }
]
